{
  "neoforge:conditions": [
    {
      "type": "neoforge:mod_loaded",
      "modid": "aquaculture"
    }
  ],
  "base_chance": 5,
  "catch_info": {
    "entity": "aquaculture:gar",
    "fish_bucket": "aquaculture:gar_bucket",
    "item": "aquaculture:gar"
  },
  "difficulty": {
    "decay": 1.0,
    "hp": 100,
    "missPenalty": 5,
    "modifiers": [],
    "speed": 9,
    "sweetspots": [
      {
        "color_as_int": 65280,
        "hitbox_size_in_pixels": 22,
        "is_flip": false,
        "moving_rate": 0.0,
        "reward": 15,
        "sweet_spot_type": "starcatcher:normal",
        "texture_path": "starcatcher:textures/gui/minigame/spots/normal.png",
        "vanishing_rate": 0.0
      },
      {
        "color_as_int": 65280,
        "hitbox_size_in_pixels": 22,
        "is_flip": false,
        "moving_rate": 0.0,
        "reward": 15,
        "sweet_spot_type": "starcatcher:normal",
        "texture_path": "starcatcher:textures/gui/minigame/spots/normal.png",
        "vanishing_rate": 0.0
      }
    ]
  },
  "has_guide_entry": true,
  "rarity": "common",
  "restrictions": [
    {
      "type": "starcatcher:dimension",
      "dimensions": [
        "minecraft:overworld"
      ],
      "dimensions_blacklist": []
    },
    {
      "type": "starcatcher:biome",
      "biomes": [],
      "biomes_blacklist": [],
      "biomes_blacklist_tags": [
        "starcatcher:is_ocean",
        "starcatcher:is_river",
        "starcatcher:is_mushroom_fields"
      ],
      "biomes_tags": [],
      "hover_translation": "gui.guide.lakes.hover",
      "translation_override": "gui.guide.lakes"
    },
    {
      "type": "starcatcher:elevation_restriction",
      "max_y": 2147483647,
      "min_y": 100,
      "translation_override": "gui.guide.elevation.mountains"
    },
    {
      "type": "starcatcher:season",
      "season_extra_chance": {
        "early_spring": 0,
        "early_winter": 0,
        "late_spring": 0,
        "late_winter": 0,
        "mid_spring": 0,
        "mid_winter": 0
      },
      "translation_override": "gui.guide.seasons.spring_winter"
    }
  ],
  "size_and_weight": {
    "average_size_cm": 160.0,
    "average_weight_grams": 160000.0,
    "deviation_size_cm": 30.0,
    "deviation_weight_grams": 20000.0,
    "golden_chance": 0.02
  },
  "skips_minigame": false
}